autocat/__init__.py
autocat/autocat.py
autocat/cli.py
autocat/detector.py
autodisambiguator-0.0.1.dist-info/LICENSE
autodisambiguator-0.0.1.dist-info/METADATA
autodisambiguator-0.0.1.dist-info/WHEEL
autodisambiguator-0.0.1.dist-info/entry_points.txt
autodisambiguator-0.0.1.dist-info/top_level.txt
autodisambiguator-0.0.1.dist-info/RECORD
